midia_compress/__init__.py
midia_compress/cli.py
midia_compress/utils/__init__.py
midia_compress/utils/helper.py
midia_compress/utils/video.py
midia_compress-0.1.0.dist-info/METADATA
midia_compress-0.1.0.dist-info/WHEEL
midia_compress-0.1.0.dist-info/entry_points.txt
midia_compress-0.1.0.dist-info/RECORD
