Metadata-Version: 2.3
Name: midia-compress
Version: 0.1.0
Summary: 
Author: Gustavo Rizzo S M de Albuquerque
Author-email: grizzo.albu@gmail.com
Requires-Python: >=3.13,<4.0
Classifier: Programming Language :: Python :: 3
Classifier: Programming Language :: Python :: 3.13
Requires-Dist: typer (>=0.16.0,<0.17.0)
